gameclock-5.1.dist-info/METADATA
gameclock-5.1.dist-info/RECORD
gameclock-5.1.dist-info/DESCRIPTION.rst
gameclock-5.1.dist-info/top_level.txt
gameclock-5.1.dist-info/WHEEL
gameclock-5.1.dist-info/metadata.json
gameclock/game.py
gameclock/gtkui.py
gameclock/__init__.py
gameclock/sound.py
gameclock/i18n.py
gameclock/clock.py
gameclock/po/fr_CA/LC_MESSAGES/gameclock.mo
gameclock-5.1.data/data/share/icons/hicolor/scalable/gameclock.svg
gameclock-5.1.data/data/share/applications/gameclock.desktop
gameclock-5.1.data/data/share/pixmaps/gameclock.xpm
gameclock-5.1.data/scripts/gameclock
