Metadata-Version: 2.0
Name: gameclock
Version: 5.1
Summary: The Gameclock
Home-page: https://0xacab.org/anarcat/gameclock/
Author: Antoine Beaupré
Author-email: anarcat@orangeseeds.org
License: GPLv3
Platform: UNKNOWN
